sessionsync/__init__.py
sessionsync/__main__.py
sessionsync/cli.py
sessionsync/git.py
sessionsync/schema.py
sessionsync/exporters/__init__.py
sessionsync/exporters/base.py
sessionsync/exporters/json.py
sessionsync/exporters/markdown.py
sessionsync/exporters/toon.py
sessionsync/parsers/__init__.py
sessionsync/parsers/base.py
sessionsync/parsers/claude_code.py
sessionsync/parsers/opencode.py
sessionsync/parsers/pi.py
sessionsync-0.1.2.dist-info/METADATA
sessionsync-0.1.2.dist-info/WHEEL
sessionsync-0.1.2.dist-info/entry_points.txt
sessionsync-0.1.2.dist-info/licenses/LICENSE
sessionsync-0.1.2.dist-info/RECORD
