Metadata-Version: 2.4
Name: sessionsync
Version: 0.1.2
Summary: CLI to export and archive coding agent sessions to multiple formats.
Project-URL: repository, https://github.com/SebastienWae/SessionSync
Project-URL: issues, https://github.com/SebastienWae/SessionSync/issues
Author-email: Sebastien Waegeneire <sebastien@waegeneire.com>
License-Expression: MIT
License-File: LICENSE
Keywords: claude-code,cli,coding-agent,export,json,markdown,opencode,session
Classifier: Development Status :: 3 - Alpha
Classifier: Environment :: Console
Classifier: Intended Audience :: Developers
Classifier: Programming Language :: Python :: 3.12
Classifier: Topic :: Software Development :: Documentation
Classifier: Topic :: Text Processing :: Markup :: Markdown
Classifier: Typing :: Typed
Requires-Python: >=3.12
Requires-Dist: cyclopts>=4.4.5
Requires-Dist: pydantic>=2.12.5
Requires-Dist: rich>=13.9
Requires-Dist: toon-format==0.9.0b1
Requires-Dist: watchdog>=6.0.0
